dj.choices-0.10.0-py2.7-nspkg.pth
dj/_choicestestproject/__init__.py
dj/_choicestestproject/manage.py
dj/_choicestestproject/settings.py
dj/_choicestestproject/urls.py
dj/_choicestestproject/app/__init__.py
dj/_choicestestproject/app/forms.py
dj/_choicestestproject/app/models.py
dj/choices/__init__.py
dj/choices/fields.py
dj/choices/tests.py
dj.choices-0.10.0.dist-info/DESCRIPTION.rst
dj.choices-0.10.0.dist-info/METADATA
dj.choices-0.10.0.dist-info/metadata.json
dj.choices-0.10.0.dist-info/namespace_packages.txt
dj.choices-0.10.0.dist-info/RECORD
dj.choices-0.10.0.dist-info/top_level.txt
dj.choices-0.10.0.dist-info/WHEEL
