Metadata-Version: 2.0
Name: dj.choices
Version: 0.10.0
Summary: An enum implementation for Django forms and models.
Home-page: https://github.com/ambv/dj.choices/
Author: Łukasz Langa
Author-email: lukasz@langa.pl
License: MIT
Keywords: django dj extra contrib choices enum enumeration
Platform: any
Classifier: Development Status :: 5 - Production/Stable
Classifier: Framework :: Django
Classifier: License :: OSI Approved :: MIT License
Classifier: Natural Language :: English
Classifier: Programming Language :: Python :: 2
Classifier: Programming Language :: Python :: 2.6
Classifier: Programming Language :: Python :: 2.7
Classifier: Programming Language :: Python :: 3
Classifier: Programming Language :: Python :: 3.2
Classifier: Programming Language :: Python :: 3.3
Classifier: Programming Language :: Python
Classifier: Topic :: Internet :: WWW/HTTP
Classifier: Topic :: Software Development :: Libraries :: Python Modules
Requires-Dist: django
Requires-Dist: six
